microdrop_plugin_manager-0.5.dist-info/DESCRIPTION.rst
microdrop_plugin_manager-0.5.dist-info/METADATA
microdrop_plugin_manager-0.5.dist-info/RECORD
microdrop_plugin_manager-0.5.dist-info/WHEEL
microdrop_plugin_manager-0.5.dist-info/entry_points.txt
microdrop_plugin_manager-0.5.dist-info/metadata.json
microdrop_plugin_manager-0.5.dist-info/top_level.txt
mpm/__init__.py
mpm/__main__.py
mpm/commands.py
mpm/hooks.py
mpm/.ropeproject/config.py
mpm/.ropeproject/globalnames
mpm/.ropeproject/history
mpm/.ropeproject/objectdb
mpm/bin/__init__.py
mpm/bin/install_dependencies.py
mpm/bin/mpm.py
mpm/bin/.ropeproject/config.py
mpm/bin/.ropeproject/globalnames
mpm/bin/.ropeproject/history
mpm/bin/.ropeproject/objectdb
