Metadata-Version: 2.0
Name: microdrop-plugin-manager
Version: 0.5
Summary: MicroDrop plugin manager.
Home-page: https://github.com/wheeler-microfluidics/mpm
Author: Christian Fobel
Author-email: christian@fobel.net
License: LGPLv2.1
Platform: UNKNOWN
Requires-Dist: configobj
Requires-Dist: path-helpers
Requires-Dist: pip-helpers (>=0.6)
Requires-Dist: progressbar2
Requires-Dist: pywin32
Requires-Dist: pyyaml
Requires-Dist: si-prefix (>=0.4.post3)
